Workbook

Sheet Daily BCRA
B1: Pases Pasivos en pesos (1) | C1: Pases Activos en pesos (1) | D1: Pases Neto | E1: LELIQ | F1: LEFI | G1: Otros (13) | H1: Mes | I1: Pases Neto | J1: LELIQ | K1: LEFI | L1: Otros | M1: F
A2: 45231 | B2: 8709890 | C2: 0 | D2: =+B2-C2 -> 8709890 | E2: 13516617 | F2: 0 | H2: =+MONTH(A2) -> 11 | I2: =+IF($H2<>$H3,D2,"") | J2: =+IF($H2<>$H3,E2,"") | K2: =+IF($H2<>$H3,F2,"") | L2: =+IF($H2<>$H3,G2,"") | M2: =+$H2<>$H3 -> FALSE
A3: 45232 | B3: 8747515 | C3: 0 | D3: =+B3-C3 -> 8747515 | E3: 13587059 | F3: 0 | H3: =+MONTH(A3) -> 11 | I3: =+IF($H3<>$H4,D3,"") | J3: =+IF($H3<>$H4,E3,"") | K3: =+IF($H3<>$H4,F3,"") | L3: =+IF($H3<>$H4,G3,"") | M3: =+$H3<>$H4 -> FALSE
A4: 45233 | B4: 9212790 | C4: 0 | D4: =+B4-C4 -> 9212790 | E4: 13587059 | F4: 0 | H4: =+MONTH(A4) -> 11 | I4: =+IF($H4<>$H5,D4,"") | J4: =+IF($H4<>$H5,E4,"") | K4: =+IF($H4<>$H5,F4,"") | L4: =+IF($H4<>$H5,G4,"") | M4: =+$H4<>$H5 -> FALSE
A5: 45237 | B5: 9217305 | C5: 0 | D5: =+B5-C5 -> 9217305 | E5: 13830515 | F5: 0 | H5: =+MONTH(A5) -> 11 | I5: =+IF($H5<>$H6,D5,"") | J5: =+IF($H5<>$H6,E5,"") | K5: =+IF($H5<>$H6,F5,"") | L5: =+IF($H5<>$H6,G5,"") | M5: =+$H5<>$H6 -> FALSE
A6: 45238 | B6: 9225716 | C6: 0 | D6: =+B6-C6 -> 9225716 | E6: 13830490 | F6: 0 | H6: =+MONTH(A6) -> 11 | I6: =+IF($H6<>$H7,D6,"") | J6: =+IF($H6<>$H7,E6,"") | K6: =+IF($H6<>$H7,F6,"") | L6: =+IF($H6<>$H7,G6,"") | M6: =+$H6<>$H7 -> FALSE
A7: 45239 | B7: 9213093 | C7: 0 | D7: =+B7-C7 -> 9213093 | E7: 14021837 | F7: 0 | H7: =+MONTH(A7) -> 11 | I7: =+IF($H7<>$H8,D7,"") | J7: =+IF($H7<>$H8,E7,"") | K7: =+IF($H7<>$H8,F7,"") | L7: =+IF($H7<>$H8,G7,"") | M7: =+$H7<>$H8 -> FALSE
A8: 45240 | B8: 9180710 | C8: 0 | D8: =+B8-C8 -> 9180710 | E8: 14021837 | F8: 0 | H8: =+MONTH(A8) -> 11 | I8: =+IF($H8<>$H9,D8,"") | J8: =+IF($H8<>$H9,E8,"") | K8: =+IF($H8<>$H9,F8,"") | L8: =+IF($H8<>$H9,G8,"") | M8: =+$H8<>$H9 -> FALSE
A9: 45243 | B9: 9157382 | C9: 0 | D9: =+B9-C9 -> 9157382 | E9: 14021837 | F9: 0 | H9: =+MONTH(A9) -> 11 | I9: =+IF($H9<>$H10,D9,"") | J9: =+IF($H9<>$H10,E9,"") | K9: =+IF($H9<>$H10,F9,"") | L9: =+IF($H9<>$H10,G9,"") | M9: =+$H9<>$H10 -> FALSE
A10: 45244 | B10: 9101064 | C10: 0 | D10: =+B10-C10 -> 9101064 | E10: 14205770 | F10: 0 | H10: =+MONTH(A10) -> 11 | I10: =+IF($H10<>$H11,D10,"") | J10: =+IF($H10<>$H11,E10,"") | K10: =+IF($H10<>$H11,F10,"") | L10: =+IF($H10<>$H11,G10,"") | M10: =+$H10<>$H11 -> FALSE
A11: 45245 | B11: 9044407 | C11: 0 | D11: =+B11-C11 -> 9044407 | E11: 14205505 | F11: 0 | H11: =+MONTH(A11) -> 11 | I11: =+IF($H11<>$H12,D11,"") | J11: =+IF($H11<>$H12,E11,"") | K11: =+IF($H11<>$H12,F11,"") | L11: =+IF($H11<>$H12,G11,"") | M11: =+$H11<>$H12 -> FALSE
A12: 45246 | B12: 9369150 | C12: 0 | D12: =+B12-C12 -> 9369150 | E12: 13975368 | F12: 0 | H12: =+MONTH(A12) -> 11 | I12: =+IF($H12<>$H13,D12,"") | J12: =+IF($H12<>$H13,E12,"") | K12: =+IF($H12<>$H13,F12,"") | L12: =+IF($H12<>$H13,G12,"") | M12: =+$H12<>$H13 -> FALSE
A13: 45247 | B13: 9199548 | C13: 0 | D13: =+B13-C13 -> 9199548 | E13: 13975368 | F13: 0 | H13: =+MONTH(A13) -> 11 | I13: =+IF($H13<>$H14,D13,"") | J13: =+IF($H13<>$H14,E13,"") | K13: =+IF($H13<>$H14,F13,"") | L13: =+IF($H13<>$H14,G13,"") | M13: =+$H13<>$H14 -> FALSE
... A411: 45852 | B411: 0 | C411: 0 | D411: =+B411-C411 -> 0 | E411: 0 | F411: 0 | H411: =+MONTH(A411) -> 7 | I411: =+IF($H411<>$H412,D411,"") | J411: =+IF($H411<>$H412,E411,"") | K411: =+IF($H411<>$H412,F411,"") | L411: =+IF($H411<>$H412,G411,"") | M411: =+$H411<>$H412 -> FALSE
A412: 45853 | B412: 0 | C412: 0 | D412: =+B412-C412 -> 0 | E412: 0 | F412: 0 | G412: 3523597.4 | H412: =+MONTH(A412) -> 7 | I412: =+IF($H412<>$H413,D412,"") | J412: =+IF($H412<>$H413,E412,"") | K412: =+IF($H412<>$H413,F412,"") | L412: =+IF($H412<>$H413,G412,"") | M412: =+$H412<>$H413 -> FALSE
A413: 45854 | B413: 0 | C413: 0 | D413: =+B413-C413 -> 0 | E413: 0 | F413: 0 | G413: 3226370.3 | H413: =+MONTH(A413) -> 7 | I413: =+IF($H413<>$H414,D413,"") | J413: =+IF($H413<>$H414,E413,"") | K413: =+IF($H413<>$H414,F413,"") | L413: =+IF($H413<>$H414,G413,"") | M413: =+$H413<>$H414 -> FALSE
A414: 45855 | B414: 0 | C414: 0 | D414: =+B414-C414 -> 0 | E414: 0 | F414: 0 | G414: 393823.68 | H414: =+MONTH(A414) -> 7 | I414: =+IF($H414<>$H415,D414,"") | J414: =+IF($H414<>$H415,E414,"") | K414: =+IF($H414<>$H415,F414,"") | L414: =+IF($H414<>$H415,G414,"") | M414: =+$H414<>$H415 -> FALSE
A415: 45856 | B415: 0 | C415: 0 | D415: =+B415-C415 -> 0 | E415: 0 | F415: 0 | G415: 2.9038347e-05 | H415: =+MONTH(A415) -> 7 | I415: =+IF($H415<>$H416,D415,"") | J415: =+IF($H415<>$H416,E415,"") | K415: =+IF($H415<>$H416,F415,"") | L415: =+IF($H415<>$H416,G415,"") | M415: =+$H415<>$H416 -> FALSE
A416: 45859 | B416: 0 | C416: 0 | D416: =+B416-C416 -> 0 | E416: 0 | F416: 0 | G416: 2.9038347e-05 | H416: =+MONTH(A416) -> 7 | I416: =+IF($H416<>$H417,D416,"") | J416: =+IF($H416<>$H417,E416,"") | K416: =+IF($H416<>$H417,F416,"") | L416: =+IF($H416<>$H417,G416,"") | M416: =+$H416<>$H417 -> FALSE
A417: 45860 | B417: 0 | C417: 0 | D417: =+B417-C417 -> 0 | E417: 0 | F417: 0 | G417: 2.9038347e-05 | H417: =+MONTH(A417) -> 7 | I417: =+IF($H417<>$H418,D417,"") | J417: =+IF($H417<>$H418,E417,"") | K417: =+IF($H417<>$H418,F417,"") | L417: =+IF($H417<>$H418,G417,"") | M417: =+$H417<>$H418 -> FALSE
A418: 45861 | B418: 0 | C418: 0 | D418: =+B418-C418 -> 0 | E418: 0 | F418: 0 | G418: 2.9038347e-05 | H418: =+MONTH(A418) -> 7 | I418: =+IF($H418<>$H419,D418,"") | J418: =+IF($H418<>$H419,E418,"") | K418: =+IF($H418<>$H419,F418,"") | L418: =+IF($H418<>$H419,G418,"") | M418: =+$H418<>$H419 -> FALSE
A419: 45862 | B419: 0 | C419: 0 | D419: =+B419-C419 -> 0 | E419: 0 | F419: 0 | G419: 2.9038347e-05 | H419: =+MONTH(A419) -> 7 | I419: =+IF($H419<>$H420,D419,"") | J419: =+IF($H419<>$H420,E419,"") | K419: =+IF($H419<>$H420,F419,"") | L419: =+IF($H419<>$H420,G419,"") | M419: =+$H419<>$H420 -> FALSE
A420: 45863 | B420: 0 | C420: 0 | D420: =+B420-C420 -> 0 | E420: 0 | F420: 0 | G420: 477121.75 | H420: =+MONTH(A420) -> 7 | I420: =+IF($H420<>$H421,D420,"") | J420: =+IF($H420<>$H421,E420,"") | K420: =+IF($H420<>$H421,F420,"") | L420: =+IF($H420<>$H421,G420,"") | M420: =+$H420<>$H421 -> FALSE
A421: 45866 | B421: 0 | C421: 0 | D421: =+B421-C421 -> 0 | E421: 0 | F421: 0 | G421: 1479753.7 | H421: =+MONTH(A421) -> 7 | I421: =+IF($H421<>$H422,D421,"") | J421: =+IF($H421<>$H422,E421,"") | K421: =+IF($H421<>$H422,F421,"") | L421: =+IF($H421<>$H422,G421,"") | M421: =+$H421<>$H422 -> FALSE
A422: 45867 | B422: 0 | C422: 0 | D422: =+B422-C422 -> 0 | E422: 0 | F422: 0 | G422: 2.9148534e-05 | H422: =+MONTH(A422) -> 7 | I422: =+IF($H422<>$H423,D422,"") | J422: =+IF($H422<>$H423,E422,"") | K422: =+IF($H422<>$H423,F422,"") | L422: =+IF($H422<>$H423,G422,"") | M422: =+$H422<>$H423 -> FALSE
A423: 45868 | B423: 0 | C423: 0 | D423: =+B423-C423 -> 0 | E423: 0 | F423: 0 | G423: 1069806.5 | H423: =+MONTH(A423) -> 7 | I423: =+IF($H423<>$H424,D423,"") | J423: =+IF($H423<>$H424,E423,"") | K423: =+IF($H423<>$H424,F423,"") | L423: =+IF($H423<>$H424,G423,"") | M423: =+$H423<>$H424 -> FALSE
... A500: 45980 | B500: 0 | C500: 0 | D500: =+B500-C500 -> 0 | E500: 0 | F500: 0 | G500: 3525736.1 | H500: =+MONTH(A500) -> 11 | I500: =+IF($H500<>$H501,D500,"") -> 0 | J500: =+IF($H500<>$H501,E500,"") -> 0 | K500: =+IF($H500<>$H501,F500,"") -> 0 | L500: =+IF($H500<>$H501,G500,"") -> 3525736.1 | M500: =+$H500<>$H501 -> TRUE

Sheet Monthly
P1: 1 | Q1: 2 | R1: 3 | S1: 4 | T1: 5 | U1: 6 | V1: 7 | W1: 8 | X1: 9
B2: Mes | C2: Pases Neto | D2: LELIQ | E2: LEFI | F2: PNM bil | G2: LEFI bil | H2: Otros | I2: Otros bill | J2: Recaudacion | K2: Gasto Primario | L2: IPC | M2: IPC | O2: Fecha | P2: Recaudacion | Q2: Gasto Primario | R2: PNM $ bill | S2: LEFI $ bill | T2: PNM + LEFI $ bill | U2: PNM + LEFI $ constantes | V2: PNM + LEFI indice | W2: Otros $ bill | X2: Otros $ constantes
A3: 45231 | B3: 11 | C3: 14699956 | D3: 7529063.5 | E3: 0 | F3: =+(C3+D3)/1000000 -> 22.229019 | G3: =E3/1000000 -> 0 | H3: 0 | I3: =+H3/1000000 -> 0 | J3: 4679610 | K3: 5151530 | L3: 2816.0628 | M3: 100 | O3: =+A3 -> 45231 | P3: =+(J3/$M3*$M$3)/J$3*100 -> 100 | Q3: =+(K3/$M3*$M$3)/K$3*100 -> 100 | R3: =+F3 -> 22.229019 | S3: =+G3 -> 0 | T3: =+R3+S3 -> 22.229019 | U3: =+T3/M3*$M$3 -> 22.229019 | V3: 100 | W3: =+I3 -> 0 | X3: =+W3/M3*$M$3 -> 0
A4: 45261 | B4: 12 | C4: 24150281 | D4: 1636551.1 | E4: 0 | F4: =+(C4+D4)/1000000 -> 25.786832 | G4: =E4/1000000 -> 0 | H4: 0 | I4: =+H4/1000000 -> 0 | J4: 5922690 | K4: 8514490 | L4: 3533.1922 | M4: =+L4*$M$3/$L$3 -> 125.46567 | O4: =+A4 -> 45261 | P4: =+(J4/$M4*$M$3)/J$3*100 -> 100.8752 | Q4: =+(K4/$M4*$M$3)/K$3*100 -> 131.73388 | R4: =+F4 -> 25.786832 | S4: =+G4 -> 0 | T4: =+R4+S4 -> 25.786832 | U4: =+T4/M4*$M$3 -> 20.552898 | V4: =+U4*$V$3/$U$3 -> 92.459759 | W4: =+I4 -> 0 | X4: =+W4/M4*$M$3 -> 0
A5: 45292 | B5: 1 | C5: 29875001 | D5: 5150 | E5: 0 | F5: =+(C5+D5)/1000000 -> 29.880151 | G5: =E5/1000000 -> 0 | H5: 0 | I5: =+H5/1000000 -> 0 | J5: 7699890 | K5: 4739150 | L5: 4261.5324 | M5: =+L5*$M$3/$L$3 -> 151.32945 | O5: =+A5 -> 45292 | P5: =+(J5/$M5*$M$3)/J$3*100 -> 108.7305 | Q5: =+(K5/$M5*$M$3)/K$3*100 -> 60.791206 | R5: =+F5 -> 29.880151 | S5: =+G5 -> 0 | T5: =+R5+S5 -> 29.880151 | U5: =+T5/M5*$M$3 -> 19.7451 | V5: =+U5*$V$3/$U$3 -> 88.825778 | W5: =+I5 -> 0 | X5: =+W5/M5*$M$3 -> 0
A6: 45323 | B6: 2 | C6: 28046328 | D6: 3000 | E6: 0 | F6: =+(C6+D6)/1000000 -> 28.049328 | G6: =E6/1000000 -> 0 | H6: 0 | I6: =+H6/1000000 -> 0 | J6: 7249310 | K6: 5085320 | L6: 4825.7881 | M6: =+L6*$M$3/$L$3 -> 171.36649 | O6: =+A6 -> 45323 | P6: =+(J6/$M6*$M$3)/J$3*100 -> 90.398474 | Q6: =+(K6/$M6*$M$3)/K$3*100 -> 57.604464 | R6: =+F6 -> 28.049328 | S6: =+G6 -> 0 | T6: =+R6+S6 -> 28.049328 | U6: =+T6/M6*$M$3 -> 16.368035 | V6: =+U6*$V$3/$U$3 -> 73.633635 | W6: =+I6 -> 0 | X6: =+W6/M6*$M$3 -> 0
A7: 45352 | B7: 3 | C7: 30791842 | D7: 0 | E7: 0 | F7: =+(C7+D7)/1000000 -> 30.791842 | G7: =E7/1000000 -> 0 | H7: 0 | I7: =+H7/1000000 -> 0 | J7: 7726460 | K7: 6385850 | L7: 5357.0929 | M7: =+L7*$M$3/$L$3 -> 190.23343 | O7: =+A7 -> 45352 | P7: =+(J7/$M7*$M$3)/J$3*100 -> 86.792872 | Q7: =+(K7/$M7*$M$3)/K$3*100 -> 65.162185 | R7: =+F7 -> 30.791842 | S7: =+G7 -> 0 | T7: =+R7+S7 -> 30.791842 | U7: =+T7/M7*$M$3 -> 16.186346 | V7: =+U7*$V$3/$U$3 -> 72.816286 | W7: =+I7 -> 0 | X7: =+W7/M7*$M$3 -> 0
A8: 45383 | B8: 4 | C8: 32712831 | D8: 0 | E8: 0 | F8: =+(C8+D8)/1000000 -> 32.712831 | G8: =E8/1000000 -> 0 | H8: 0 | I8: =+H8/1000000 -> 0 | J8: 8663810 | K8: 7625760 | L8: 5830.2271 | M8: =+L8*$M$3/$L$3 -> 207.0347 | O8: =+A8 -> 45383 | P8: =+(J8/$M8*$M$3)/J$3*100 -> 89.424418 | Q8: =+(K8/$M8*$M$3)/K$3*100 -> 71.499625 | R8: =+F8 -> 32.712831 | S8: =+G8 -> 0 | T8: =+R8+S8 -> 32.712831 | U8: =+T8/M8*$M$3 -> 15.800651 | V8: =+U8*$V$3/$U$3 -> 71.08119 | W8: =+I8 -> 0 | X8: =+W8/M8*$M$3 -> 0
A9: 45413 | B9: 5 | C9: 18489248 | D9: 0 | E9: 0 | F9: =+(C9+D9)/1000000 -> 18.489248 | G9: =E9/1000000 -> 0 | H9: 0 | I9: =+H9/1000000 -> 0 | J9: 13379400 | K9: 8148500 | L9: 6073.7165 | M9: =+L9*$M$3/$L$3 -> 215.68115 | O9: =+A9 -> 45413 | P9: =+(J9/$M9*$M$3)/J$3*100 -> 132.5607 | Q9: =+(K9/$M9*$M$3)/K$3*100 -> 73.338033 | R9: =+F9 -> 18.489248 | S9: =+G9 -> 0 | T9: =+R9+S9 -> 18.489248 | U9: =+T9/M9*$M$3 -> 8.5724916 | V9: =+U9*$V$3/$U$3 -> 38.564416 | W9: =+I9 -> 0 | X9: =+W9/M9*$M$3 -> 0
A10: 45444 | B10: 6 | C10: 15880749 | D10: 0 | E10: 0 | F10: =+(C10+D10)/1000000 -> 15.880749 | G10: =E10/1000000 -> 0 | H10: 0 | I10: =+H10/1000000 -> 0 | J10: 11297600 | K10: 10451200 | L10: 6351.7145 | M10: =+L10*$M$3/$L$3 -> 225.55301 | O10: =+A10 -> 45444 | P10: =+(J10/$M10*$M$3)/J$3*100 -> 107.03551 | Q10: =+(K10/$M10*$M$3)/K$3*100 -> 89.945884 | R10: =+F10 -> 15.880749 | S10: =+G10 -> 0 | T10: =+R10+S10 -> 15.880749 | U10: =+T10/M10*$M$3 -> 7.0408055 | V10: =+U10*$V$3/$U$3 -> 31.673937 | W10: =+I10 -> 0 | X10: =+W10/M10*$M$3 -> 0
A11: 45474 | B11: 7 | C11: 0 | D11: 0 | E11: 9604955.5 | F11: =+(C11+D11)/1000000 -> 0 | G11: =E11/1000000 -> 9.6049555 | H11: 0 | I11: =+H11/1000000 -> 0 | J11: 11910500 | K11: 9960450 | L11: 6607.7479 | M11: =+L11*$M$3/$L$3 -> 234.64491 | O11: =+A11 -> 45474 | P11: =+(J11/$M11*$M$3)/J$3*100 -> 108.46989 | Q11: =+(K11/$M11*$M$3)/K$3*100 -> 82.400832 | R11: =+F11 -> 0 | S11: =+G11 -> 9.6049555 | T11: =+R11+S11 -> 9.6049555 | U11: =+T11/M11*$M$3 -> 4.0934004 | V11: =+U11*$V$3/$U$3 -> 18.414669 | W11: =+I11 -> 0 | X11: =+W11/M11*$M$3 -> 0
A12: 45505 | B12: 8 | C12: 0 | D12: 0 | E12: 8828310.7 | F12: =+(C12+D12)/1000000 -> 0 | G12: =E12/1000000 -> 8.8283107 | H12: 0 | I12: =+H12/1000000 -> 0 | J12: 11764100 | K12: 9399770 | L12: 6883.4412 | M12: =+L12*$M$3/$L$3 -> 244.43493 | O12: =+A12 -> 45505 | P12: =+(J12/$M12*$M$3)/J$3*100 -> 102.84561 | Q12: =+(K12/$M12*$M$3)/K$3*100 -> 74.647922 | R12: =+F12 -> 0 | S12: =+G12 -> 8.8283107 | T12: =+R12+S12 -> 8.8283107 | U12: =+T12/M12*$M$3 -> 3.6117222 | V12: =+U12*$V$3/$U$3 -> 16.24778 | W12: =+I12 -> 0 | X12: =+W12/M12*$M$3 -> 0
A13: 45536 | B13: 9 | C13: -164436 | D13: 0 | E13: 11143865 | F13: =+(C13+D13)/1000000 -> -0.164436 | G13: =E13/1000000 -> 11.143865 | H13: 0 | I13: =+H13/1000000 -> 0 | J13: 12844500 | K13: 9828970 | L13: 7122.2421 | M13: =+L13*$M$3/$L$3 -> 252.91489 | O13: =+A13 -> 45536 | P13: =+(J13/$M13*$M$3)/J$3*100 -> 108.52584 | Q13: =+(K13/$M13*$M$3)/K$3*100 -> 75.439253 | R13: =+F13 -> -0.164436 | S13: =+G13 -> 11.143865 | T13: =+R13+S13 -> 10.979429 | U13: =+T13/M13*$M$3 -> 4.3411557 | V13: =+U13*$V$3/$U$3 -> 19.529227 | W13: =+I13 -> 0 | X13: =+W13/M13*$M$3 -> 0
A14: 45566 | B14: 10 | C14: -50389 | D14: 0 | E14: 12677889 | F14: =+(C14+D14)/1000000 -> -0.050389 | G14: =E14/1000000 -> 12.677889 | H14: 0 | I14: =+H14/1000000 -> 0 | J14: 12780400 | K14: 10609500 | L14: 7313.9542 | M14: =+L14*$M$3/$L$3 -> 259.7227 | O14: =+A14 -> 45566 | P14: =+(J14/$M14*$M$3)/J$3*100 -> 105.15378 | Q14: =+(K14/$M14*$M$3)/K$3*100 -> 79.295544 | R14: =+F14 -> -0.050389 | S14: =+G14 -> 12.677889 | T14: =+R14+S14 -> 12.6275 | U14: =+T14/M14*$M$3 -> 4.8619164 | V14: =+U14*$V$3/$U$3 -> 21.871934 | W14: =+I14 -> 0 | X14: =+W14/M14*$M$3 -> 0
A15: 45597 | B15: 11 | C15: -263134 | D15: 0 | E15: 14915259 | F15: =+(C15+D15)/1000000 -> -0.263134 | G15: =E15/1000000 -> 14.915259 | H15: 0 | I15: =+H15/1000000 -> 0 | J15: 13026400 | K15: 10957300 | L15: 7491.4314 | M15: =+L15*$M$3/$L$3 -> 266.02501 | O15: =+A15 -> 45597 | P15: =+(J15/$M15*$M$3)/J$3*100 -> 104.63869 | Q15: =+(K15/$M15*$M$3)/K$3*100 -> 79.954856 | R15: =+F15 -> -0.263134 | S15: =+G15 -> 14.915259 | T15: =+R15+S15 -> 14.652125 | U15: =+T15/M15*$M$3 -> 5.5077996 | V15: =+U15*$V$3/$U$3 -> 24.777519 | W15: =+I15 -> 0 | X15: =+W15/M15*$M$3 -> 0
... A26: 45931 | B26: 10 | C26: 0 | D26: 0 | E26: 0 | F26: =+(C26+D26)/1000000 -> 0 | G26: =E26/1000000 -> 0 | H26: 3595523.1 | I26: =+H26/1000000 -> 3.5955231 | J26: 16165700 | K26: 13686000 | L26: 9603.8623 | M26: =+L26*$M$3/$L$3 -> 341.03864 | O26: =+A26 -> 45931 | P26: =+(J26/$M26*$M$3)/J$3*100 -> 101.29343 | Q26: =+(K26/$M26*$M$3)/K$3*100 -> 77.899867 | R26: =+F26 -> 0 | S26: =+G26 -> 0 | T26: =+R26+S26 -> 0 | U26: =+T26/M26*$M$3 -> 0 | V26: =+U26*$V$3/$U$3 -> 0 | W26: =+I26 -> 3.5955231 | X26: =+W26/M26*$M$3 -> 1.0542861
A27: 45962 | B27: 11 | C27: 0 | D27: 0 | E27: 0 | F27: =+(C27+D27)/1000000 -> 0 | G27: =E27/1000000 -> 0 | H27: 3525736.1 | I27: =+H27/1000000 -> 3.5257361

Sheet T1
B1: =Monthly!P1 -> 1 | C1: =Monthly!Q1 -> 2 | D1: =Monthly!R1 -> 3 | E1: =Monthly!S1 -> 4 | F1: =Monthly!T1 -> 5 | G1: =Monthly!U1 -> 6 | H1: =Monthly!V1 -> 7
A2: =Monthly!O2 -> Fecha | B2: =Monthly!P2 -> Recaudacion | C2: =Monthly!Q2 -> Gasto Primario | D2: =Monthly!R2 -> PNM $ bill | E2: =Monthly!S2 -> LEFI $ bill | F2: =Monthly!T2 -> PNM + LEFI $ bill | G2: =Monthly!U2 -> PNM + LEFI $ constantes | H2: =Monthly!V2 -> PNM + LEFI indice
A3: =Monthly!O3 -> 45231 | B3: =Monthly!P3 -> 100 | C3: =Monthly!Q3 -> 100 | D3: =Monthly!R3 -> 22.229019 | E3: =Monthly!S3 -> 0 | F3: =Monthly!T3 -> 22.229019 | G3: =Monthly!U3 -> 22.229019 | H3: =Monthly!V3 -> 100
A4: =Monthly!O4 -> 45261 | B4: =Monthly!P4 -> 100.8752 | C4: =Monthly!Q4 -> 131.73388 | D4: =Monthly!R4 -> 25.786832 | E4: =Monthly!S4 -> 0 | F4: =Monthly!T4 -> 25.786832 | G4: =Monthly!U4 -> 20.552898 | H4: =Monthly!V4 -> 92.459759
A5: =Monthly!O5 -> 45292 | B5: =Monthly!P5 -> 108.7305 | C5: =Monthly!Q5 -> 60.791206 | D5: =Monthly!R5 -> 29.880151 | E5: =Monthly!S5 -> 0 | F5: =Monthly!T5 -> 29.880151 | G5: =Monthly!U5 -> 19.7451 | H5: =Monthly!V5 -> 88.825778
A6: =Monthly!O6 -> 45323 | B6: =Monthly!P6 -> 90.398474 | C6: =Monthly!Q6 -> 57.604464 | D6: =Monthly!R6 -> 28.049328 | E6: =Monthly!S6 -> 0 | F6: =Monthly!T6 -> 28.049328 | G6: =Monthly!U6 -> 16.368035 | H6: =Monthly!V6 -> 73.633635
A7: =Monthly!O7 -> 45352 | B7: =Monthly!P7 -> 86.792872 | C7: =Monthly!Q7 -> 65.162185 | D7: =Monthly!R7 -> 30.791842 | E7: =Monthly!S7 -> 0 | F7: =Monthly!T7 -> 30.791842 | G7: =Monthly!U7 -> 16.186346 | H7: =Monthly!V7 -> 72.816286
A8: =Monthly!O8 -> 45383 | B8: =Monthly!P8 -> 89.424418 | C8: =Monthly!Q8 -> 71.499625 | D8: =Monthly!R8 -> 32.712831 | E8: =Monthly!S8 -> 0 | F8: =Monthly!T8 -> 32.712831 | G8: =Monthly!U8 -> 15.800651 | H8: =Monthly!V8 -> 71.08119
A9: =Monthly!O9 -> 45413 | B9: =Monthly!P9 -> 132.5607 | C9: =Monthly!Q9 -> 73.338033 | D9: =Monthly!R9 -> 18.489248 | E9: =Monthly!S9 -> 0 | F9: =Monthly!T9 -> 18.489248 | G9: =Monthly!U9 -> 8.5724916 | H9: =Monthly!V9 -> 38.564416
A10: =Monthly!O10 -> 45444 | B10: =Monthly!P10 -> 107.03551 | C10: =Monthly!Q10 -> 89.945884 | D10: =Monthly!R10 -> 15.880749 | E10: =Monthly!S10 -> 0 | F10: =Monthly!T10 -> 15.880749 | G10: =Monthly!U10 -> 7.0408055 | H10: =Monthly!V10 -> 31.673937
A11: =Monthly!O11 -> 45474 | B11: =Monthly!P11 -> 108.46989 | C11: =Monthly!Q11 -> 82.400832 | D11: =Monthly!R11 -> 0 | E11: =Monthly!S11 -> 9.6049555 | F11: =Monthly!T11 -> 9.6049555 | G11: =Monthly!U11 -> 4.0934004 | H11: =Monthly!V11 -> 18.414669
A12: =Monthly!O12 -> 45505 | B12: =Monthly!P12 -> 102.84561 | C12: =Monthly!Q12 -> 74.647922 | D12: =Monthly!R12 -> 0 | E12: =Monthly!S12 -> 8.8283107 | F12: =Monthly!T12 -> 8.8283107 | G12: =Monthly!U12 -> 3.6117222 | H12: =Monthly!V12 -> 16.24778
A13: =Monthly!O13 -> 45536 | B13: =Monthly!P13 -> 108.52584 | C13: =Monthly!Q13 -> 75.439253 | D13: =Monthly!R13 -> -0.164436 | E13: =Monthly!S13 -> 11.143865 | F13: =Monthly!T13 -> 10.979429 | G13: =Monthly!U13 -> 4.3411557 | H13: =Monthly!V13 -> 19.529227
... A26: =Monthly!O26 -> 45931 | B26: =Monthly!P26 -> 101.29343 | C26: =Monthly!Q26 -> 77.899867 | D26: =Monthly!R26 -> 0 | E26: =Monthly!S26 -> 0 | F26: =Monthly!T26 -> 0 | G26: =Monthly!U26 -> 0 | H26: =Monthly!V26 -> 0

Sheet T2
C1: $ bill | D1: u$s millones | E1: s/ var. BM neta
A2: 1 | B2: Var BM | C2: =11090981/1000000 -> 11.090981 | D2: 9301
A3: 2 | B3: Sup SPNF | C3: =12517672/1000000 -> 12.517672 | D3: 10669
A4: 3 | B4: Pagos Deuda Pub. | C4: - | D4: 5933
A5: 4 | B5: Sup - Pagos | C5: - | D5: =+D3-D4 -> 4736
A6: 5 | B6: Var BM neta | C6: - | D6: =+D2-D5 -> 4565 | E6: =+D6/$D$6 -> 1
A7: 6 | B7: Acum RI | C7: - | D7: =+D6 -> 4565 | E7: =+D7/$D$6 -> 1
A8: 7 | B8: Canc LEFI | C8: - | D8: -
A9: 8 | B9: Falta p/ LEFI | C9: - | D9: -
